<pkg-contents spec="1.12"><f n="LittleShoot" o="adamfisk" g="wheel" p="16893" pt="/Users/adamfisk/temp_install_dir/trunk/install/osx/LittleShoot" m="true" t="file"><f n=".svn" o="adamfisk" g="wheel" p="16893" x="true"><f n="all-wcprops" o="adamfisk" g="wheel" p="33204" x="true"/><f n="entries" o="adamfisk" g="wheel" p="33204" x="true"/><f n="format" o="adamfisk" g="wheel" p="33204" x="true"/><f n="prop-base" o="adamfisk" g="wheel" p="16893" x="true"><f n=".VolumeIcon.icns.svn-base" o="adamfisk" g="wheel" p="33204" x="true"/></f><f n="props" o="adamfisk" g="wheel" p="16893" x="true"/><f n="text-base" o="adamfisk" g="wheel" p="16893" x="true"><f n=".VolumeIcon.icns.svn-base" o="adamfisk" g="wheel" p="33204" x="true"/></f><f n="tmp" o="adamfisk" g="wheel" p="16893" x="true"><f n="prop-base" o="adamfisk" g="wheel" p="16893" x="true"/><f n="props" o="adamfisk" g="wheel" p="16893" x="true"/><f n="text-base" o="adamfisk" g="wheel" p="16893" x="true"/></f></f><f n=".VolumeIcon.icns" o="adamfisk" g="wheel" p="33204"/><f n="component" o="adamfisk" g="wheel" p="16893"><f n=".svn" o="adamfisk" g="wheel" p="16893" x="true"><f n="all-wcprops" o="adamfisk" g="wheel" p="33204" x="true"><mod>mode</mod></f><f n="entries" o="adamfisk" g="wheel" p="33204" x="true"><mod>mode</mod></f><f n="format" o="adamfisk" g="wheel" p="33204" x="true"><mod>mode</mod></f><f n="prop-base" o="adamfisk" g="wheel" p="16893" x="true"><mod>mode</mod></f><f n="props" o="adamfisk" g="wheel" p="16893" x="true"><mod>mode</mod></f><f n="text-base" o="adamfisk" g="wheel" p="16893" x="true"><f n="org.lastbamboo.littleshoot.plist.svn-base" o="adamfisk" g="wheel" p="33204" x="true"><mod>mode</mod></f><mod>mode</mod></f><f n="tmp" o="adamfisk" g="wheel" p="16893" x="true"><f n="prop-base" o="adamfisk" g="wheel" p="16893" x="true"><mod>mode</mod></f><f n="props" o="adamfisk" g="wheel" p="16893" x="true"><mod>mode</mod></f><f n="text-base" o="adamfisk" g="wheel" p="16893" x="true"><mod>mode</mod></f><mod>mode</mod></f><mod>mode</mod></f><f n="LittleShoot.app" o="adamfisk" g="wheel" p="16893"><f n="Contents" o="adamfisk" g="wheel" p="16893"><f n="Info.plist" o="adamfisk" g="wheel" p="33204"><mod>mode</mod></f><f n="MacOS" o="adamfisk" g="wheel" p="16893"><f n="LittleShoot" o="adamfisk" g="wheel" p="33277"><mod>mode</mod></f><mod>mode</mod></f><f n="Resources" o="adamfisk" g="wheel" p="16893"><f n="Java" o="adamfisk" g="wheel" p="16893"><f n="aopalliance-1.0.jar.pack" o="adamfisk" g="wheel" p="33204"><mod>mode</mod></f><f n="clink-0.6-lw-1.jar.pack" o="adamfisk" g="wheel" p="33204"><mod>mode</mod></f><f n="cocoaFoundation-1.jar.pack" o="adamfisk" g="wheel" p="33204"><mod>mode</mod></f><f n="commons-codec-1.2.jar.pack" o="adamfisk" g="wheel" p="33204"><mod>mode</mod></f><f n="commons-collections-3.2.jar.pack" o="adamfisk" g="wheel" p="33204"><mod>mode</mod></f><f n="commons-discovery-0.2.jar.pack" o="adamfisk" g="wheel" p="33204"><mod>mode</mod></f><f n="commons-httpclient-3.1.jar.pack" o="adamfisk" g="wheel" p="33204"><mod>mode</mod></f><f n="commons-id-0.1.jar.pack" o="adamfisk" g="wheel" p="33204"><mod>mode</mod></f><f n="commons-io-1.4.jar.pack" o="adamfisk" g="wheel" p="33204"><mod>mode</mod></f><f n="commons-lang-2.4.jar.pack" o="adamfisk" g="wheel" p="33204"><mod>mode</mod></f><f n="commons-logging-1.1.1.jar.pack" o="adamfisk" g="wheel" p="33204"><mod>mode</mod></f><f n="commons-net-1.4.1.jar.pack" o="adamfisk" g="wheel" p="33204"><mod>mode</mod></f><f n="dnsjava-2.0.6.jar.pack" o="adamfisk" g="wheel" p="33204"><mod>mode</mod></f><f n="guice-1.0.jar.pack" o="adamfisk" g="wheel" p="33204"><mod>mode</mod></f><f n="hsqldb-1.8.0.8.jar.pack" o="adamfisk" g="wheel" p="33204"><mod>mode</mod></f><f n="httpclient-4.0-beta1.jar.pack" o="adamfisk" g="wheel" p="33204"><mod>mode</mod></f><f n="httpcore-4.0-beta2.jar.pack" o="adamfisk" g="wheel" p="33204"><mod>mode</mod></f><f n="httpcore-nio-4.0-beta2.jar.pack" o="adamfisk" g="wheel" p="33204"><mod>mode</mod></f><f n="icu4j-3.4.4.jar.pack" o="adamfisk" g="wheel" p="33204"><mod>mode</mod></f><f n="id3v2-0.3-lw-1.jar.pack" o="adamfisk" g="wheel" p="33204"><mod>mode</mod></f><f n="jaudiotagger-1.0.jar.pack" o="adamfisk" g="wheel" p="33204"><mod>mode</mod></f><f n="jcl104-over-slf4j-1.4.0.jar.pack" o="adamfisk" g="wheel" p="33204"><mod>mode</mod></f><f n="je-3.3.75.jar.pack" o="adamfisk" g="wheel" p="33204"><mod>mode</mod></f><f n="jetty-6.1.11.jar.pack" o="adamfisk" g="wheel" p="33204"><mod>mode</mod></f><f n="jetty-util-6.1.11.jar.pack" o="adamfisk" g="wheel" p="33204"><mod>mode</mod></f><f n="jogg-0.0.7.jar.pack" o="adamfisk" g="wheel" p="33204"><mod>mode</mod></f><f n="jorbis-0.0.15.jar.pack" o="adamfisk" g="wheel" p="33204"><mod>mode</mod></f><f n="lastbamboo-client-controllers-1.0.jar.pack" o="adamfisk" g="wheel" p="33204"><mod>mode</mod></f><f n="lastbamboo-client-http-server-1.0.jar.pack" o="adamfisk" g="wheel" p="33204"><mod>mode</mod></f><f n="lastbamboo-client-launcher-all-1.0.jar.pack" o="adamfisk" g="wheel" p="33204"><mod>mode</mod></f><f n="lastbamboo-client-prefs-1.0.jar.pack" o="adamfisk" g="wheel" p="33204"><mod>mode</mod></f><f n="lastbamboo-client-resource-1.0.jar.pack" o="adamfisk" g="wheel" p="33204"><mod>mode</mod></f><f n="lastbamboo-client-search-1.0.jar.pack" o="adamfisk" g="wheel" p="33204"><mod>mode</mod></f><f n="lastbamboo-client-services-1.0.jar.pack" o="adamfisk" g="wheel" p="33204"><mod>mode</mod></f><f n="lastbamboo-client-site-1.0.jar.pack" o="adamfisk" g="wheel" p="33204"><mod>mode</mod></f><f n="lastbamboo-client-util-1.0.jar.pack" o="adamfisk" g="wheel" p="33204"><mod>mode</mod></f><f n="lastbamboo-common-amazon-ec2-1.0.jar.pack" o="adamfisk" g="wheel" p="33204"><mod>mode</mod></f><f n="lastbamboo-common-amazon-stack-1.0.jar.pack" o="adamfisk" g="wheel" p="33204"><mod>mode</mod></f><f n="lastbamboo-common-bencode-1.0.jar.pack" o="adamfisk" g="wheel" p="33204"><mod>mode</mod></f><f n="lastbamboo-common-controllers-1.0.jar.pack" o="adamfisk" g="wheel" p="33204"><mod>mode</mod></f><f n="lastbamboo-common-download-1.0.jar.pack" o="adamfisk" g="wheel" p="33204"><mod>mode</mod></f><f n="lastbamboo-common-http-client-1.0.jar.pack" o="adamfisk" g="wheel" p="33204"><mod>mode</mod></f><f n="lastbamboo-common-ice-1.0.jar.pack" o="adamfisk" g="wheel" p="33204"><mod>mode</mod></f><f n="lastbamboo-common-ice-rudp-1.0.jar.pack" o="adamfisk" g="wheel" p="33204"><mod>mode</mod></f><f n="lastbamboo-common-jlibtorrent-1.0.jar.pack" o="adamfisk" g="wheel" p="33204"><mod>mode</mod></f><f n="lastbamboo-common-json-1.0.jar.pack" o="adamfisk" g="wheel" p="33204"><mod>mode</mod></f><f n="lastbamboo-common-log4j-bug-appender-1.0.jar.pack" o="adamfisk" g="wheel" p="33204"><mod>mode</mod></f><f n="lastbamboo-common-npapi-1.0.jar.pack" o="adamfisk" g="wheel" p="33204"><mod>mode</mod></f><f n="lastbamboo-common-offer-answer-1.0.jar.pack" o="adamfisk" g="wheel" p="33204"><mod>mode</mod></f><f n="lastbamboo-common-online-1.0.jar.pack" o="adamfisk" g="wheel" p="33204"><mod>mode</mod></f><f n="lastbamboo-common-rest-1.0.jar.pack" o="adamfisk" g="wheel" p="33204"><mod>mode</mod></f><f n="lastbamboo-common-rudp-1.0.jar.pack" o="adamfisk" g="wheel" p="33204"><mod>mode</mod></f><f n="lastbamboo-common-sdp-1.0.jar.pack" o="adamfisk" g="wheel" p="33204"><mod>mode</mod></f><f n="lastbamboo-common-searchers-flickr-1.0.jar.pack" o="adamfisk" g="wheel" p="33204"><mod>mode</mod></f><f n="lastbamboo-common-searchers-isohunt-1.0.jar.pack" o="adamfisk" g="wheel" p="33204"><mod>mode</mod></f><f n="lastbamboo-common-searchers-limewire-1.0.jar.pack" o="adamfisk" g="wheel" p="33204"><mod>mode</mod></f><f n="lastbamboo-common-searchers-littleshoot-1.0.jar.pack" o="adamfisk" g="wheel" p="33204"><mod>mode</mod></f><f n="lastbamboo-common-searchers-yahoo-1.0.jar.pack" o="adamfisk" g="wheel" p="33204"><mod>mode</mod></f><f n="lastbamboo-common-searchers-youtube-1.0.jar.pack" o="adamfisk" g="wheel" p="33204"><mod>mode</mod></f><f n="lastbamboo-common-services-1.0.jar.pack" o="adamfisk" g="wheel" p="33204"><mod>mode</mod></f><f n="lastbamboo-common-sip-bootstrap-1.0.jar.pack" o="adamfisk" g="wheel" p="33204"><mod>mode</mod></f><f n="lastbamboo-common-sip-client-1.0.jar.pack" o="adamfisk" g="wheel" p="33204"><mod>mode</mod></f><f n="lastbamboo-common-sip-http-client-1.0.jar.pack" o="adamfisk" g="wheel" p="33204"><mod>mode</mod></f><f n="lastbamboo-common-sip-proxy-1.0.jar.pack" o="adamfisk" g="wheel" p="33204"><mod>mode</mod></f><f n="lastbamboo-common-sip-stack-1.0.jar.pack" o="adamfisk" g="wheel" p="33204"><mod>mode</mod></f><f n="lastbamboo-common-stun-client-1.0.jar.pack" o="adamfisk" g="wheel" p="33204"><mod>mode</mod></f><f n="lastbamboo-common-stun-server-1.0.jar.pack" o="adamfisk" g="wheel" p="33204"><mod>mode</mod></f><f n="lastbamboo-common-stun-stack-1.0.jar.pack" o="adamfisk" g="wheel" p="33204"><mod>mode</mod></f><f n="lastbamboo-common-tcp-framing-1.0.jar.pack" o="adamfisk" g="wheel" p="33204"><mod>mode</mod></f><f n="lastbamboo-common-turn-client-1.0.jar.pack" o="adamfisk" g="wheel" p="33204"><mod>mode</mod></f><f n="lastbamboo-common-turn-http-server-1.0.jar.pack" o="adamfisk" g="wheel" p="33204"><mod>mode</mod></f><f n="lastbamboo-common-turn-server-1.0.jar.pack" o="adamfisk" g="wheel" p="33204"><mod>mode</mod></f><f n="lastbamboo-common-upnp-1.0.jar.pack" o="adamfisk" g="wheel" p="33204"><mod>mode</mod></f><f n="lastbamboo-common-util-common-1.0.jar.pack" o="adamfisk" g="wheel" p="33204"><mod>mode</mod></f><f n="lastbamboo-common-util-mina-1.0.jar.pack" o="adamfisk" g="wheel" p="33204"><mod>mode</mod></f><f n="lastbamboo-jni-jlibtorrent-1.0.jar.pack" o="adamfisk" g="wheel" p="33204"><mod>mode</mod></f><f n="libjnltorrent.jnilib" o="adamfisk" g="wheel" p="33204"><mod>mode</mod></f><f n="littleShoot.keystore" o="adamfisk" g="wheel" p="33204"><mod>mode</mod></f><f n="log4j-1.2.14.jar.pack" o="adamfisk" g="wheel" p="33204"><mod>mode</mod></f><f n="log4j.properties" o="adamfisk" g="wheel" p="33204"><mod>mode</mod></f><f n="lw-collection-4.18.8.jar.pack" o="adamfisk" g="wheel" p="33204"><mod>mode</mod></f><f n="lw-common-4.18.8.jar.pack" o="adamfisk" g="wheel" p="33204"><mod>mode</mod></f><f n="lw-core-4.18.8.jar.pack" o="adamfisk" g="wheel" p="33204"><mod>mode</mod></f><f n="lw-geocode-4.18.8.jar.pack" o="adamfisk" g="wheel" p="33204"><mod>mode</mod></f><f n="lw-http-4.18.8.jar.pack" o="adamfisk" g="wheel" p="33204"><mod>mode</mod></f><f n="lw-io-4.18.8.jar.pack" o="adamfisk" g="wheel" p="33204"><mod>mode</mod></f><f n="lw-lib-4.18.8.jar.pack" o="adamfisk" g="wheel" p="33204"><mod>mode</mod></f><f n="lw-lwsserver-4.18.8.jar.pack" o="adamfisk" g="wheel" p="33204"><mod>mode</mod></f><f n="lw-net-4.18.8.jar.pack" o="adamfisk" g="wheel" p="33204"><mod>mode</mod></f><f n="lw-nio-4.18.8.jar.pack" o="adamfisk" g="wheel" p="33204"><mod>mode</mod></f><f n="lw-promotion-4.18.8.jar.pack" o="adamfisk" g="wheel" p="33204"><mod>mode</mod></f><f n="lw-resources-4.18.8.jar.pack" o="adamfisk" g="wheel" p="33204"><mod>mode</mod></f><f n="lw-rudp-4.18.8.jar.pack" o="adamfisk" g="wheel" p="33204"><mod>mode</mod></f><f n="lw-security-4.18.8.jar.pack" o="adamfisk" g="wheel" p="33204"><mod>mode</mod></f><f n="lw-setting-4.18.8.jar.pack" o="adamfisk" g="wheel" p="33204"><mod>mode</mod></f><f n="lw-statistic-4.18.8.jar.pack" o="adamfisk" g="wheel" p="33204"><mod>mode</mod></f><f n="mina-core-1.1.7.jar.pack" o="adamfisk" g="wheel" p="33204"><mod>mode</mod></f><f n="mojito-1.0-SNAPSHOT.jar.pack" o="adamfisk" g="wheel" p="33204"><mod>mode</mod></f><f n="onion-common-1.0.jar.pack" o="adamfisk" g="wheel" p="33204"><mod>mode</mod></f><f n="onion-fec-1.0.jar.pack" o="adamfisk" g="wheel" p="33204"><mod>mode</mod></f><f n="oro-2.0.8.jar.pack" o="adamfisk" g="wheel" p="33204"><mod>mode</mod></f><f n="servlet-api-2.4.jar.pack" o="adamfisk" g="wheel" p="33204"><mod>mode</mod></f><f n="servlet-api-2.5-6.1.11.jar.pack" o="adamfisk" g="wheel" p="33204"><mod>mode</mod></f><f n="slf4j-api-1.4.0.jar.pack" o="adamfisk" g="wheel" p="33204"><mod>mode</mod></f><f n="slf4j-log4j12-1.4.0.jar.pack" o="adamfisk" g="wheel" p="33204"><mod>mode</mod></f><f n="spring-beans-2.5.3.jar.pack" o="adamfisk" g="wheel" p="33204"><mod>mode</mod></f><f n="spring-context-2.5.3.jar.pack" o="adamfisk" g="wheel" p="33204"><mod>mode</mod></f><f n="spring-context-support-2.5.3.jar.pack" o="adamfisk" g="wheel" p="33204"><mod>mode</mod></f><f n="spring-core-2.5.3.jar.pack" o="adamfisk" g="wheel" p="33204"><mod>mode</mod></f><f n="spring-web-2.5.3.jar.pack" o="adamfisk" g="wheel" p="33204"><mod>mode</mod></f><f n="spring-webmvc-2.5.3.jar.pack" o="adamfisk" g="wheel" p="33204"><mod>mode</mod></f><f n="src" o="adamfisk" g="wheel" p="16893"><f n="main" o="adamfisk" g="wheel" p="16893"><f n="webapp" o="adamfisk" g="wheel" p="16893"><f n=".svn" o="adamfisk" g="wheel" p="16893"><f n="all-wcprops" o="adamfisk" g="wheel" p="33204"><mod>mode</mod></f><f n="entries" o="adamfisk" g="wheel" p="33204"><mod>mode</mod></f><f n="format" o="adamfisk" g="wheel" p="33204"><mod>mode</mod></f><f n="prop-base" o="adamfisk" g="wheel" p="16893"><f n="favicon.ico.svn-base" o="adamfisk" g="wheel" p="33204"><mod>mode</mod></f><mod>mode</mod></f><f n="props" o="adamfisk" g="wheel" p="16893"><mod>mode</mod></f><f n="text-base" o="adamfisk" g="wheel" p="16893"><f n="crossdomain.xml.svn-base" o="adamfisk" g="wheel" p="33204"><mod>mode</mod></f><f n="favicon.ico.svn-base" o="adamfisk" g="wheel" p="33204"><mod>mode</mod></f><mod>mode</mod></f><f n="tmp" o="adamfisk" g="wheel" p="16893"><f n="prop-base" o="adamfisk" g="wheel" p="16893"><mod>mode</mod></f><f n="props" o="adamfisk" g="wheel" p="16893"><mod>mode</mod></f><f n="text-base" o="adamfisk" g="wheel" p="16893"><mod>mode</mod></f><mod>mode</mod></f><mod>mode</mod></f><f n="crossdomain.xml" o="adamfisk" g="wheel" p="33204"><mod>mode</mod></f><f n="favicon.ico" o="adamfisk" g="wheel" p="33204"><mod>mode</mod></f><f n="WEB-INF" o="adamfisk" g="wheel" p="16893"><f n=".svn" o="adamfisk" g="wheel" p="16893"><f n="all-wcprops" o="adamfisk" g="wheel" p="33204"><mod>mode</mod></f><f n="entries" o="adamfisk" g="wheel" p="33204"><mod>mode</mod></f><f n="format" o="adamfisk" g="wheel" p="33204"><mod>mode</mod></f><f n="prop-base" o="adamfisk" g="wheel" p="16893"><mod>mode</mod></f><f n="props" o="adamfisk" g="wheel" p="16893"><mod>mode</mod></f><f n="text-base" o="adamfisk" g="wheel" p="16893"><f n="activate-dev-pay-servlet.xml.svn-base" o="adamfisk" g="wheel" p="33204"><mod>mode</mod></f><f n="app-check-servlet.xml.svn-base" o="adamfisk" g="wheel" p="33204"><mod>mode</mod></f><f n="applicationContext.xml.svn-base" o="adamfisk" g="wheel" p="33204"><mod>mode</mod></f><f n="clear-failed-downloads-servlet.xml.svn-base" o="adamfisk" g="wheel" p="33204"><mod>mode</mod></f><f n="clear-inactive-downloads-servlet.xml.svn-base" o="adamfisk" g="wheel" p="33204"><mod>mode</mod></f><f n="crossdomain-servlet.xml.svn-base" o="adamfisk" g="wheel" p="33204"><mod>mode</mod></f><f n="directory-redirect-servlet.xml.svn-base" o="adamfisk" g="wheel" p="33204"><mod>mode</mod></f><f n="download-servlet.xml.svn-base" o="adamfisk" g="wheel" p="33204"><mod>mode</mod></f><f n="download-status-servlet.xml.svn-base" o="adamfisk" g="wheel" p="33204"><mod>mode</mod></f><f n="download-stream-servlet.xml.svn-base" o="adamfisk" g="wheel" p="33204"><mod>mode</mod></f><f n="download-torrent-servlet.xml.svn-base" o="adamfisk" g="wheel" p="33204"><mod>mode</mod></f><f n="downloads-servlet.xml.svn-base" o="adamfisk" g="wheel" p="33204"><mod>mode</mod></f><f n="http-urn-sha1-servlet.xml.svn-base" o="adamfisk" g="wheel" p="33204"><mod>mode</mod></f><f n="pause-download-servlet.xml.svn-base" o="adamfisk" g="wheel" p="33204"><mod>mode</mod></f><f n="pending-files-servlet.xml.svn-base" o="adamfisk" g="wheel" p="33204"><mod>mode</mod></f><f n="publish-file-servlet.xml.svn-base" o="adamfisk" g="wheel" p="33204"><mod>mode</mod></f><f n="remove-file-servlet.xml.svn-base" o="adamfisk" g="wheel" p="33204"><mod>mode</mod></f><f n="resume-download-servlet.xml.svn-base" o="adamfisk" g="wheel" p="33204"><mod>mode</mod></f><f n="search-results-servlet.xml.svn-base" o="adamfisk" g="wheel" p="33204"><mod>mode</mod></f><f n="search-servlet.xml.svn-base" o="adamfisk" g="wheel" p="33204"><mod>mode</mod></f><f n="signed-relay-servlet.xml.svn-base" o="adamfisk" g="wheel" p="33204"><mod>mode</mod></f><f n="start-download-servlet.xml.svn-base" o="adamfisk" g="wheel" p="33204"><mod>mode</mod></f><f n="stop-download-servlet.xml.svn-base" o="adamfisk" g="wheel" p="33204"><mod>mode</mod></f><f n="web.xml.svn-base" o="adamfisk" g="wheel" p="33204"><mod>mode</mod></f><mod>mode</mod></f><f n="tmp" o="adamfisk" g="wheel" p="16893"><f n="prop-base" o="adamfisk" g="wheel" p="16893"><mod>mode</mod></f><f n="props" o="adamfisk" g="wheel" p="16893"><mod>mode</mod></f><f n="text-base" o="adamfisk" g="wheel" p="16893"><mod>mode</mod></f><mod>mode</mod></f><mod>mode</mod></f><f n="activate-dev-pay-servlet.xml" o="adamfisk" g="wheel" p="33204"><mod>mode</mod></f><f n="app-check-servlet.xml" o="adamfisk" g="wheel" p="33204"><mod>mode</mod></f><f n="applicationContext.xml" o="adamfisk" g="wheel" p="33204"><mod>mode</mod></f><f n="clear-failed-downloads-servlet.xml" o="adamfisk" g="wheel" p="33204"><mod>mode</mod></f><f n="clear-inactive-downloads-servlet.xml" o="adamfisk" g="wheel" p="33204"><mod>mode</mod></f><f n="crossdomain-servlet.xml" o="adamfisk" g="wheel" p="33204"><mod>mode</mod></f><f n="directory-redirect-servlet.xml" o="adamfisk" g="wheel" p="33204"><mod>mode</mod></f><f n="download-servlet.xml" o="adamfisk" g="wheel" p="33204"><mod>mode</mod></f><f n="download-status-servlet.xml" o="adamfisk" g="wheel" p="33204"><mod>mode</mod></f><f n="download-stream-servlet.xml" o="adamfisk" g="wheel" p="33204"><mod>mode</mod></f><f n="download-torrent-servlet.xml" o="adamfisk" g="wheel" p="33204"><mod>mode</mod></f><f n="downloads-servlet.xml" o="adamfisk" g="wheel" p="33204"><mod>mode</mod></f><f n="http-urn-sha1-servlet.xml" o="adamfisk" g="wheel" p="33204"><mod>mode</mod></f><f n="pause-download-servlet.xml" o="adamfisk" g="wheel" p="33204"><mod>mode</mod></f><f n="pending-files-servlet.xml" o="adamfisk" g="wheel" p="33204"><mod>mode</mod></f><f n="publish-file-servlet.xml" o="adamfisk" g="wheel" p="33204"><mod>mode</mod></f><f n="remove-file-servlet.xml" o="adamfisk" g="wheel" p="33204"><mod>mode</mod></f><f n="resume-download-servlet.xml" o="adamfisk" g="wheel" p="33204"><mod>mode</mod></f><f n="search-results-servlet.xml" o="adamfisk" g="wheel" p="33204"><mod>mode</mod></f><f n="search-servlet.xml" o="adamfisk" g="wheel" p="33204"><mod>mode</mod></f><f n="signed-relay-servlet.xml" o="adamfisk" g="wheel" p="33204"><mod>mode</mod></f><f n="start-download-servlet.xml" o="adamfisk" g="wheel" p="33204"><mod>mode</mod></f><f n="stop-download-servlet.xml" o="adamfisk" g="wheel" p="33204"><mod>mode</mod></f><f n="web.xml" o="adamfisk" g="wheel" p="33204"><mod>mode</mod></f><mod>mode</mod></f><mod>mode</mod></f><mod>mode</mod></f><mod>mode</mod></f><mod>mode</mod></f><f n="LittleShoot.icns" o="adamfisk" g="wheel" p="33204"><mod>mode</mod></f><mod>mode</mod></f><mod>mode</mod></f><mod>mode</mod></f><f n="LittleShootLauncher.app" o="adamfisk" g="wheel" p="16893"><f n=".svn" o="adamfisk" g="wheel" p="16893"><f n="all-wcprops" o="adamfisk" g="wheel" p="33204"><mod>mode</mod></f><f n="entries" o="adamfisk" g="wheel" p="33204"><mod>mode</mod></f><f n="format" o="adamfisk" g="wheel" p="33204"><mod>mode</mod></f><f n="prop-base" o="adamfisk" g="wheel" p="16893"><mod>mode</mod></f><f n="props" o="adamfisk" g="wheel" p="16893"><mod>mode</mod></f><f n="text-base" o="adamfisk" g="wheel" p="16893"><mod>mode</mod></f><f n="tmp" o="adamfisk" g="wheel" p="16893"><f n="prop-base" o="adamfisk" g="wheel" p="16893"><mod>mode</mod></f><f n="props" o="adamfisk" g="wheel" p="16893"><mod>mode</mod></f><f n="text-base" o="adamfisk" g="wheel" p="16893"><mod>mode</mod></f><mod>mode</mod></f><mod>mode</mod></f><f n="Contents" o="adamfisk" g="wheel" p="16893"><f n=".svn" o="adamfisk" g="wheel" p="16893"><f n="all-wcprops" o="adamfisk" g="wheel" p="33204"><mod>mode</mod></f><f n="entries" o="adamfisk" g="wheel" p="33204"><mod>mode</mod></f><f n="format" o="adamfisk" g="wheel" p="33204"><mod>mode</mod></f><f n="prop-base" o="adamfisk" g="wheel" p="16893"><mod>mode</mod></f><f n="props" o="adamfisk" g="wheel" p="16893"><mod>mode</mod></f><f n="text-base" o="adamfisk" g="wheel" p="16893"><f n="Info.plist.svn-base" o="adamfisk" g="wheel" p="33204"><mod>mode</mod></f><f n="PkgInfo.svn-base" o="adamfisk" g="wheel" p="33204"><mod>mode</mod></f><mod>mode</mod></f><f n="tmp" o="adamfisk" g="wheel" p="16893"><f n="prop-base" o="adamfisk" g="wheel" p="16893"><mod>mode</mod></f><f n="props" o="adamfisk" g="wheel" p="16893"><mod>mode</mod></f><f n="text-base" o="adamfisk" g="wheel" p="16893"><mod>mode</mod></f><mod>mode</mod></f><mod>mode</mod></f><f n="Info.plist" o="adamfisk" g="wheel" p="33204"><mod>mode</mod></f><f n="MacOS" o="adamfisk" g="wheel" p="16893"><f n=".svn" o="adamfisk" g="wheel" p="16893"><f n="all-wcprops" o="adamfisk" g="wheel" p="33204"><mod>mode</mod></f><f n="entries" o="adamfisk" g="wheel" p="33204"><mod>mode</mod></f><f n="format" o="adamfisk" g="wheel" p="33204"><mod>mode</mod></f><f n="prop-base" o="adamfisk" g="wheel" p="16893"><f n="applet.svn-base" o="adamfisk" g="wheel" p="33204"><mod>mode</mod></f><mod>mode</mod></f><f n="props" o="adamfisk" g="wheel" p="16893"><mod>mode</mod></f><f n="text-base" o="adamfisk" g="wheel" p="16893"><f n="applet.svn-base" o="adamfisk" g="wheel" p="33277"><mod>mode</mod></f><mod>mode</mod></f><f n="tmp" o="adamfisk" g="wheel" p="16893"><f n="prop-base" o="adamfisk" g="wheel" p="16893"><mod>mode</mod></f><f n="props" o="adamfisk" g="wheel" p="16893"><mod>mode</mod></f><f n="text-base" o="adamfisk" g="wheel" p="16893"><mod>mode</mod></f><mod>mode</mod></f><mod>mode</mod></f><f n="applet" o="adamfisk" g="wheel" p="33277"><mod>mode</mod></f><mod>mode</mod></f><f n="PkgInfo" o="adamfisk" g="wheel" p="33204"><mod>mode</mod></f><f n="Resources" o="adamfisk" g="wheel" p="16893"><f n=".svn" o="adamfisk" g="wheel" p="16893"><f n="all-wcprops" o="adamfisk" g="wheel" p="33204"><mod>mode</mod></f><f n="entries" o="adamfisk" g="wheel" p="33204"><mod>mode</mod></f><f n="format" o="adamfisk" g="wheel" p="33204"><mod>mode</mod></f><f n="prop-base" o="adamfisk" g="wheel" p="16893"><f n="applet.icns.svn-base" o="adamfisk" g="wheel" p="33204"><mod>mode</mod></f><f n="applet.rsrc.svn-base" o="adamfisk" g="wheel" p="33204"><mod>mode</mod></f><mod>mode</mod></f><f n="props" o="adamfisk" g="wheel" p="16893"><mod>mode</mod></f><f n="text-base" o="adamfisk" g="wheel" p="16893"><f n="applet.icns.svn-base" o="adamfisk" g="wheel" p="33204"><mod>mode</mod></f><f n="applet.rsrc.svn-base" o="adamfisk" g="wheel" p="33204"><mod>mode</mod></f><mod>mode</mod></f><f n="tmp" o="adamfisk" g="wheel" p="16893"><f n="prop-base" o="adamfisk" g="wheel" p="16893"><mod>mode</mod></f><f n="props" o="adamfisk" g="wheel" p="16893"><mod>mode</mod></f><f n="text-base" o="adamfisk" g="wheel" p="16893"><mod>mode</mod></f><mod>mode</mod></f><mod>mode</mod></f><f n="applet.icns" o="adamfisk" g="wheel" p="33204"><mod>mode</mod></f><f n="applet.rsrc" o="adamfisk" g="wheel" p="33204"><mod>mode</mod></f><f n="description.rtfd" o="adamfisk" g="wheel" p="16893"><f n=".svn" o="adamfisk" g="wheel" p="16893"><f n="all-wcprops" o="adamfisk" g="wheel" p="33204"><mod>mode</mod></f><f n="entries" o="adamfisk" g="wheel" p="33204"><mod>mode</mod></f><f n="format" o="adamfisk" g="wheel" p="33204"><mod>mode</mod></f><f n="prop-base" o="adamfisk" g="wheel" p="16893"><mod>mode</mod></f><f n="props" o="adamfisk" g="wheel" p="16893"><mod>mode</mod></f><f n="text-base" o="adamfisk" g="wheel" p="16893"><f n="TXT.rtf.svn-base" o="adamfisk" g="wheel" p="33204"><mod>mode</mod></f><mod>mode</mod></f><f n="tmp" o="adamfisk" g="wheel" p="16893"><f n="prop-base" o="adamfisk" g="wheel" p="16893"><mod>mode</mod></f><f n="props" o="adamfisk" g="wheel" p="16893"><mod>mode</mod></f><f n="text-base" o="adamfisk" g="wheel" p="16893"><mod>mode</mod></f><mod>mode</mod></f><mod>mode</mod></f><f n="TXT.rtf" o="adamfisk" g="wheel" p="33204"><mod>mode</mod></f><mod>mode</mod></f><f n="Scripts" o="adamfisk" g="wheel" p="16893"><f n=".svn" o="adamfisk" g="wheel" p="16893"><f n="all-wcprops" o="adamfisk" g="wheel" p="33204"><mod>mode</mod></f><f n="entries" o="adamfisk" g="wheel" p="33204"><mod>mode</mod></f><f n="format" o="adamfisk" g="wheel" p="33204"><mod>mode</mod></f><f n="prop-base" o="adamfisk" g="wheel" p="16893"><f n="main.scpt.svn-base" o="adamfisk" g="wheel" p="33204"><mod>mode</mod></f><mod>mode</mod></f><f n="props" o="adamfisk" g="wheel" p="16893"><mod>mode</mod></f><f n="text-base" o="adamfisk" g="wheel" p="16893"><f n="main.scpt.svn-base" o="adamfisk" g="wheel" p="33204"><mod>mode</mod></f><mod>mode</mod></f><f n="tmp" o="adamfisk" g="wheel" p="16893"><f n="prop-base" o="adamfisk" g="wheel" p="16893"><mod>mode</mod></f><f n="props" o="adamfisk" g="wheel" p="16893"><mod>mode</mod></f><f n="text-base" o="adamfisk" g="wheel" p="16893"><mod>mode</mod></f><mod>mode</mod></f><mod>mode</mod></f><f n="main.scpt" o="adamfisk" g="wheel" p="33204"><mod>mode</mod></f><mod>mode</mod></f><mod>mode</mod></f><mod>mode</mod></f><mod>mode</mod></f><f n="LittleShootPlugIn.plugin" o="adamfisk" g="wheel" p="16893"><f n="Contents" o="adamfisk" g="wheel" p="16893"><f n="Info.plist" o="adamfisk" g="wheel" p="33204"><mod>mode</mod></f><f n="MacOS" o="adamfisk" g="wheel" p="16893"><f n="LittleShootPlugIn" o="adamfisk" g="wheel" p="33277"><mod>mode</mod></f><mod>mode</mod></f><f n="Resources" o="adamfisk" g="wheel" p="16893"><f n="English.lproj" o="adamfisk" g="wheel" p="16893"><f n="InfoPlist.strings" o="adamfisk" g="wheel" p="33204"><mod>mode</mod></f><f n="Localized.rsrc" o="adamfisk" g="wheel" p="33204"><mod>mode</mod></f><f n="version.plist" o="adamfisk" g="wheel" p="33204"><mod>mode</mod></f><mod>mode</mod></f><mod>mode</mod></f><mod>mode</mod></f><mod>mode</mod></f><f n="LittleShootUninstaller.app" o="adamfisk" g="wheel" p="16893"><f n=".svn" o="adamfisk" g="wheel" p="16893"><f n="all-wcprops" o="adamfisk" g="wheel" p="33204"><mod>mode</mod></f><f n="entries" o="adamfisk" g="wheel" p="33204"><mod>mode</mod></f><f n="format" o="adamfisk" g="wheel" p="33204"><mod>mode</mod></f><f n="prop-base" o="adamfisk" g="wheel" p="16893"><mod>mode</mod></f><f n="props" o="adamfisk" g="wheel" p="16893"><mod>mode</mod></f><f n="text-base" o="adamfisk" g="wheel" p="16893"><mod>mode</mod></f><f n="tmp" o="adamfisk" g="wheel" p="16893"><f n="prop-base" o="adamfisk" g="wheel" p="16893"><mod>mode</mod></f><f n="props" o="adamfisk" g="wheel" p="16893"><mod>mode</mod></f><f n="text-base" o="adamfisk" g="wheel" p="16893"><mod>mode</mod></f><mod>mode</mod></f><mod>mode</mod></f><f n="Contents" o="adamfisk" g="wheel" p="16893"><f n=".svn" o="adamfisk" g="wheel" p="16893"><f n="all-wcprops" o="adamfisk" g="wheel" p="33204"><mod>mode</mod></f><f n="entries" o="adamfisk" g="wheel" p="33204"><mod>mode</mod></f><f n="format" o="adamfisk" g="wheel" p="33204"><mod>mode</mod></f><f n="prop-base" o="adamfisk" g="wheel" p="16893"><mod>mode</mod></f><f n="props" o="adamfisk" g="wheel" p="16893"><mod>mode</mod></f><f n="text-base" o="adamfisk" g="wheel" p="16893"><f n="Info.plist.svn-base" o="adamfisk" g="wheel" p="33204"><mod>mode</mod></f><f n="PkgInfo.svn-base" o="adamfisk" g="wheel" p="33204"><mod>mode</mod></f><mod>mode</mod></f><f n="tmp" o="adamfisk" g="wheel" p="16893"><f n="prop-base" o="adamfisk" g="wheel" p="16893"><mod>mode</mod></f><f n="props" o="adamfisk" g="wheel" p="16893"><mod>mode</mod></f><f n="text-base" o="adamfisk" g="wheel" p="16893"><mod>mode</mod></f><mod>mode</mod></f><mod>mode</mod></f><f n="Info.plist" o="adamfisk" g="wheel" p="33204"><mod>mode</mod></f><f n="MacOS" o="adamfisk" g="wheel" p="16893"><f n=".svn" o="adamfisk" g="wheel" p="16893"><f n="all-wcprops" o="adamfisk" g="wheel" p="33204"><mod>mode</mod></f><f n="entries" o="adamfisk" g="wheel" p="33204"><mod>mode</mod></f><f n="format" o="adamfisk" g="wheel" p="33204"><mod>mode</mod></f><f n="prop-base" o="adamfisk" g="wheel" p="16893"><f n="applet.svn-base" o="adamfisk" g="wheel" p="33204"><mod>mode</mod></f><mod>mode</mod></f><f n="props" o="adamfisk" g="wheel" p="16893"><mod>mode</mod></f><f n="text-base" o="adamfisk" g="wheel" p="16893"><f n="applet.svn-base" o="adamfisk" g="wheel" p="33277"><mod>mode</mod></f><mod>mode</mod></f><f n="tmp" o="adamfisk" g="wheel" p="16893"><f n="prop-base" o="adamfisk" g="wheel" p="16893"><mod>mode</mod></f><f n="props" o="adamfisk" g="wheel" p="16893"><mod>mode</mod></f><f n="text-base" o="adamfisk" g="wheel" p="16893"><mod>mode</mod></f><mod>mode</mod></f><mod>mode</mod></f><f n="applet" o="adamfisk" g="wheel" p="33277"><mod>mode</mod></f><mod>mode</mod></f><f n="PkgInfo" o="adamfisk" g="wheel" p="33204"><mod>mode</mod></f><f n="Resources" o="adamfisk" g="wheel" p="16893"><f n=".svn" o="adamfisk" g="wheel" p="16893"><f n="all-wcprops" o="adamfisk" g="wheel" p="33204"><mod>mode</mod></f><f n="entries" o="adamfisk" g="wheel" p="33204"><mod>mode</mod></f><f n="format" o="adamfisk" g="wheel" p="33204"><mod>mode</mod></f><f n="prop-base" o="adamfisk" g="wheel" p="16893"><f n="applet.icns.svn-base" o="adamfisk" g="wheel" p="33204"><mod>mode</mod></f><f n="applet.rsrc.svn-base" o="adamfisk" g="wheel" p="33204"><mod>mode</mod></f><mod>mode</mod></f><f n="props" o="adamfisk" g="wheel" p="16893"><mod>mode</mod></f><f n="text-base" o="adamfisk" g="wheel" p="16893"><f n="applet.icns.svn-base" o="adamfisk" g="wheel" p="33204"><mod>mode</mod></f><f n="applet.rsrc.svn-base" o="adamfisk" g="wheel" p="33204"><mod>mode</mod></f><f n="uninstall.bash.svn-base" o="adamfisk" g="wheel" p="33277"><mod>mode</mod></f><mod>mode</mod></f><f n="tmp" o="adamfisk" g="wheel" p="16893"><f n="prop-base" o="adamfisk" g="wheel" p="16893"><mod>mode</mod></f><f n="props" o="adamfisk" g="wheel" p="16893"><mod>mode</mod></f><f n="text-base" o="adamfisk" g="wheel" p="16893"><mod>mode</mod></f><mod>mode</mod></f><mod>mode</mod></f><f n="applet.icns" o="adamfisk" g="wheel" p="33204"><mod>mode</mod></f><f n="applet.rsrc" o="adamfisk" g="wheel" p="33204"><mod>mode</mod></f><f n="description.rtfd" o="adamfisk" g="wheel" p="16893"><f n=".svn" o="adamfisk" g="wheel" p="16893"><f n="all-wcprops" o="adamfisk" g="wheel" p="33204"><mod>mode</mod></f><f n="entries" o="adamfisk" g="wheel" p="33204"><mod>mode</mod></f><f n="format" o="adamfisk" g="wheel" p="33204"><mod>mode</mod></f><f n="prop-base" o="adamfisk" g="wheel" p="16893"><mod>mode</mod></f><f n="props" o="adamfisk" g="wheel" p="16893"><mod>mode</mod></f><f n="text-base" o="adamfisk" g="wheel" p="16893"><f n="TXT.rtf.svn-base" o="adamfisk" g="wheel" p="33204"><mod>mode</mod></f><mod>mode</mod></f><f n="tmp" o="adamfisk" g="wheel" p="16893"><f n="prop-base" o="adamfisk" g="wheel" p="16893"><mod>mode</mod></f><f n="props" o="adamfisk" g="wheel" p="16893"><mod>mode</mod></f><f n="text-base" o="adamfisk" g="wheel" p="16893"><mod>mode</mod></f><mod>mode</mod></f><mod>mode</mod></f><f n="TXT.rtf" o="adamfisk" g="wheel" p="33204"><mod>mode</mod></f><mod>mode</mod></f><f n="Scripts" o="adamfisk" g="wheel" p="16893"><f n=".svn" o="adamfisk" g="wheel" p="16893"><f n="all-wcprops" o="adamfisk" g="wheel" p="33204"><mod>mode</mod></f><f n="entries" o="adamfisk" g="wheel" p="33204"><mod>mode</mod></f><f n="format" o="adamfisk" g="wheel" p="33204"><mod>mode</mod></f><f n="prop-base" o="adamfisk" g="wheel" p="16893"><f n="main.scpt.svn-base" o="adamfisk" g="wheel" p="33204"><mod>mode</mod></f><mod>mode</mod></f><f n="props" o="adamfisk" g="wheel" p="16893"><mod>mode</mod></f><f n="text-base" o="adamfisk" g="wheel" p="16893"><f n="main.scpt.svn-base" o="adamfisk" g="wheel" p="33204"><mod>mode</mod></f><mod>mode</mod></f><f n="tmp" o="adamfisk" g="wheel" p="16893"><f n="prop-base" o="adamfisk" g="wheel" p="16893"><mod>mode</mod></f><f n="props" o="adamfisk" g="wheel" p="16893"><mod>mode</mod></f><f n="text-base" o="adamfisk" g="wheel" p="16893"><mod>mode</mod></f><mod>mode</mod></f><mod>mode</mod></f><f n="main.scpt" o="adamfisk" g="wheel" p="33204"><mod>mode</mod></f><mod>mode</mod></f><f n="uninstall.bash" o="adamfisk" g="wheel" p="33277"><mod>mode</mod></f><mod>mode</mod></f><mod>mode</mod></f><mod>mode</mod></f><f n="org.lastbamboo.littleshoot.plist" o="adamfisk" g="wheel" p="33204"><mod>mode</mod></f><mod>mode</mod></f><f n="extras" o="adamfisk" g="wheel" p="16893"><f n=".svn" o="adamfisk" g="wheel" p="16893" x="true"><f n="all-wcprops" o="adamfisk" g="wheel" p="33204" x="true"><mod>mode</mod></f><f n="entries" o="adamfisk" g="wheel" p="33204" x="true"><mod>mode</mod></f><f n="format" o="adamfisk" g="wheel" p="33204" x="true"><mod>mode</mod></f><f n="prop-base" o="adamfisk" g="wheel" p="16893" x="true"><f n="postflight.svn-base" o="adamfisk" g="wheel" p="33204" x="true"><mod>mode</mod></f><mod>mode</mod></f><f n="props" o="adamfisk" g="wheel" p="16893" x="true"><mod>mode</mod></f><f n="text-base" o="adamfisk" g="wheel" p="16893" x="true"><f n="postflight.svn-base" o="adamfisk" g="wheel" p="33277" x="true"><mod>mode</mod></f><mod>mode</mod></f><f n="tmp" o="adamfisk" g="wheel" p="16893" x="true"><f n="prop-base" o="adamfisk" g="wheel" p="16893" x="true"><mod>mode</mod></f><f n="props" o="adamfisk" g="wheel" p="16893" x="true"><mod>mode</mod></f><f n="text-base" o="adamfisk" g="wheel" p="16893" x="true"><mod>mode</mod></f><mod>mode</mod></f><mod>mode</mod></f><f n="postflight" o="adamfisk" g="wheel" p="33277"><mod>mode</mod></f><mod>mode</mod></f></f></pkg-contents>